[
  {
    "category": "C&C domain",
    "severity": "High",
    "dns_type": "A",
    "technologies": ["URL Reputation", "Targeted Attack Analyzer"]
  },
  {
    "category": "DGA domain",
    "severity": "High",
    "dns_type": "A",
    "technologies": ["Targeted Attack Analyzer"]
  },
  {
    "category": "Phishing domain",
    "severity": "Medium",
    "dns_type": "A",
    "technologies": ["URL Reputation"]
  },
  {
    "category": "Malware distribution domain",
    "severity": "High",
    "dns_type": "A",
    "technologies": ["URL Reputation"]
  },
  {
    "category": "DNS tunneling",
    "severity": "High",
    "dns_type": "TXT",
    "technologies": ["Targeted Attack Analyzer"]
  },
  {
    "category": "Suspicious newly registered domain",
    "severity": "Low",
    "dns_type": "A",
    "technologies": ["URL Reputation"]
  }
]
